fancyprint/__init__.py
fancyprint/printer.py
fancyprint/ftypes/__init__.py
fancyprint/ftypes/align.py
fancyprint/ftypes/color.py
fancyprint/ftypes/preset.py
fancyprint/ftypes/printer_preset.py
fancyprint/ftypes/separator_preset.py
fancyprint/presets/__init__.py
fancyprint/presets/ascii/__init__.py
fancyprint/presets/unicode/__init__.py
fancyprint-0.1.5.dist-info/WHEEL
fancyprint-0.1.5.dist-info/METADATA
fancyprint-0.1.5.dist-info/RECORD
