Metadata-Version: 2.1
Name: fancyprint
Version: 0.1.5
Summary: A aesthetic replacement to print()
Author-email: MU <iammu@duck.com>
Requires-Python: >=3.7
Classifier: Programming Language :: Python :: 3
Classifier: License :: OSI Approved :: Apache Software License
Classifier: Operating System :: OS Independent
Project-URL: Bug Tracker, https://github.com/IamMU/Fancy-Print/issues
Project-URL: Homepage, https://github.com/IamMU/Fancy-Print
